MANIFEST.in
README
application.py
package_extender.py
setup.cfg
setup.py
__deploy__/__init__.py
__deploy__/ally/__init__.py
__deploy__/ally/deploy.py
__deploy__/ally/prepare.py
__deploy__/ally_http_mongrel2_server/__init__.py
__deploy__/ally_http_mongrel2_server/deploy.py
__deploy__/ally_http_mongrel2_server/prepare.py
__deploy__/ally_plugin/__init__.py
__deploy__/ally_plugin/deploy.py
__plugin__/__init__.py
__plugin__/acl/__init__.py
__plugin__/acl/acl.py
__plugin__/acl/gui.py
__plugin__/acl/security.py
__plugin__/administration/__init__.py
__plugin__/administration/actions.py
__plugin__/administration/gui.py
__plugin__/administration/service.py
__plugin__/administration/gui-resources/__init__.py
__plugin__/administration/gui-resources/scripts/__init__.py
__plugin__/administration/gui-resources/scripts/js/__init__.py
__plugin__/administration/gui-resources/templates/__init__.py
__plugin__/ally_plugin/__init__.py
__plugin__/ally_plugin/distribution.py
__plugin__/captcha/__init__.py
__plugin__/captcha/acl.py
__plugin__/captcha/patch_ally_core.py
__plugin__/captcha/patch_ally_core_http.py
__plugin__/captcha/patch_service_gateway_recaptcha.py
__plugin__/captcha/service.py
__plugin__/cdm/__init__.py
__plugin__/cdm/patch_mongrel2_server.py
__plugin__/gateway/__init__.py
__plugin__/gateway/patch_ally_core_http.py
__plugin__/gateway/patch_service_gateway.py
__plugin__/gateway/service.py
__plugin__/gui_action/__init__.py
__plugin__/gui_action/defaults.py
__plugin__/gui_action/service.py
__plugin__/gui_core/__init__.py
__plugin__/gui_core/gui_core.py
__plugin__/gui_core/gui_lib.py
__plugin__/gui_core/service.py
__plugin__/gui_core/gui-resources/__init__.py
__plugin__/gui_core/gui-resources/start.html
__plugin__/gui_core/gui-resources/fonts/FontAwesome.otf
__plugin__/gui_core/gui-resources/fonts/fontawesome-webfont.eot
__plugin__/gui_core/gui-resources/fonts/fontawesome-webfont.svg
__plugin__/gui_core/gui-resources/fonts/fontawesome-webfont.ttf
ally_py.egg-info/PKG-INFO
ally_py.egg-info/SOURCES.txt
ally_py.egg-info/dependency_links.txt
ally_py.egg-info/requires.txt
ally_py.egg-info/top_level.txt
ally_py.egg-info/zip-safe
