Metadata-Version: 1.1
Name: ally-py
Version: 0.9.0
Summary: Ally-Py
Home-page: http://www.sourcefabric.org/en/superdesk/
Author: Sourcefabric
Author-email: contact@sourcefabric.org
License: GPL v3
Keywords: Liveblog
Platform: all
Classifier: Development Status :: 5 - Production/Stable
Classifier: Environment :: Console
Classifier: Intended Audience :: Developers
Classifier: License :: OSI Approved :: GNU General Public License v3 (GPLv3)
Classifier: Operating System :: OS Independent
Classifier: Programming Language :: Python :: 3.2
Classifier: Topic :: Software Development :: Libraries :: Application Frameworks
